filever/__init__.py
filever/loadfile.py
filever-1.0.1.data/scripts/fver
filever-1.0.1.data/scripts/fver.py
filever-1.0.1.dist-info/LICENSE.md
filever-1.0.1.dist-info/METADATA
filever-1.0.1.dist-info/WHEEL
filever-1.0.1.dist-info/top_level.txt
filever-1.0.1.dist-info/RECORD
