Metadata-Version: 2.1
Name: filever
Version: 1.0.1
Summary: filever: cli file backup solution.
Home-page: https://github.com/monotone-the-musical/filever
Author: mtm
Author-email: MTM <monotone.the.musical@gmail.com>
Project-URL: Homepage, https://github.com/monotone-the-musical/filever
Project-URL: Bug Tracker, https://github.com/monotone-the-musical/filever/issues
Classifier: Programming Language :: Python :: 3
Classifier: License :: OSI Approved :: MIT License
Classifier: Operating System :: POSIX :: Linux
License-File: LICENSE.md
Requires-Dist: pick (>2.0.0)
